aiomonobnk/__init__.py
aiomonobnk/client/__init__.py
aiomonobnk/client/client.py
aiomonobnk/client/context.py
aiomonobnk/client/session/__init__.py
aiomonobnk/client/session/base.py
aiomonobnk/client/session/middlewares/__init__.py
aiomonobnk/client/session/middlewares/base.py
aiomonobnk/client/session/middlewares/manager.py
aiomonobnk/client/session/session.py
aiomonobnk/enums/__init__.py
aiomonobnk/enums/account_type.py
aiomonobnk/enums/amount_type.py
aiomonobnk/enums/cancellation_status.py
aiomonobnk/enums/cashback_type.py
aiomonobnk/enums/check_status.py
aiomonobnk/enums/check_type.py
aiomonobnk/enums/currency_code.py
aiomonobnk/enums/fiscalization_source.py
aiomonobnk/enums/initiation_kind.py
aiomonobnk/enums/payment_method.py
aiomonobnk/enums/payment_scheme.py
aiomonobnk/enums/payment_type.py
aiomonobnk/enums/registration_status.py
aiomonobnk/enums/tokenized_card_status.py
aiomonobnk/enums/transaction_status.py
aiomonobnk/exceptions.py
aiomonobnk/methods/__init__.py
aiomonobnk/methods/base.py
aiomonobnk/methods/cancel_invoice.py
aiomonobnk/methods/create_invoice.py
aiomonobnk/methods/delete_card.py
aiomonobnk/methods/direct_payment.py
aiomonobnk/methods/finalize_invoice.py
aiomonobnk/methods/fiscal_checks.py
aiomonobnk/methods/invoice_status.py
aiomonobnk/methods/merchant_details.py
aiomonobnk/methods/merchant_pubkey.py
aiomonobnk/methods/merchant_statement.py
aiomonobnk/methods/payment_info.py
aiomonobnk/methods/qr_details.py
aiomonobnk/methods/qr_list.py
aiomonobnk/methods/qr_reset_amount.py
aiomonobnk/methods/remove_invoice.py
aiomonobnk/methods/submerchant_list.py
aiomonobnk/methods/wallet_cards.py
aiomonobnk/methods/wallet_payment.py
aiomonobnk/mono.py
aiomonobnk/types/__init__.py
aiomonobnk/types/account.py
aiomonobnk/types/base.py
aiomonobnk/types/canceled_item.py
aiomonobnk/types/card_data.py
aiomonobnk/types/check.py
aiomonobnk/types/check_list.py
aiomonobnk/types/currency.py
aiomonobnk/types/empty_response.py
aiomonobnk/types/invoice_canceled.py
aiomonobnk-0.5.5.dist-info/METADATA
aiomonobnk-0.5.5.dist-info/WHEEL
aiomonobnk-0.5.5.dist-info/RECORD
